databar/__init__.py
databar/connection.py
databar/helpers.py
databar/table.py
databar-0.5.0.dist-info/LICENSE
databar-0.5.0.dist-info/METADATA
databar-0.5.0.dist-info/WHEEL
databar-0.5.0.dist-info/top_level.txt
databar-0.5.0.dist-info/RECORD
