Metadata-Version: 2.1
Name: databar
Version: 0.5.0
Summary: Official Databar.ai python package
Home-page: https://github.com/databar-ai/databar-python
Author: Databar.ai Team
Author-email: founders@databar.ai
License: MIT
Requires-Python: >=3.8
License-File: LICENSE
Requires-Dist: pandas (==1.4.2)
Requires-Dist: requests (==2.28.2)
Requires-Dist: aiohttp (==3.8.1)
Requires-Dist: tabulate (==0.9.0)
Provides-Extra: develop
Requires-Dist: black ; extra == 'develop'
Requires-Dist: coverage ; extra == 'develop'
Requires-Dist: flake8 ; extra == 'develop'
Requires-Dist: isort ; extra == 'develop'
Requires-Dist: mypy ; extra == 'develop'
Requires-Dist: pytest ; extra == 'develop'
Requires-Dist: pylint ; extra == 'develop'
Requires-Dist: sphinx ; extra == 'develop'
Requires-Dist: sphinx-rtd-theme ; extra == 'develop'
